nimbus_splash/__init__.py
nimbus_splash/__version__.py
nimbus_splash/cli.py
nimbus_splash/config.py
nimbus_splash/job.py
nimbus_splash/utils.py
nimbus_splash-1.13.10.dist-info/licenses/LICENSE
nimbus_splash-1.13.10.dist-info/METADATA
nimbus_splash-1.13.10.dist-info/WHEEL
nimbus_splash-1.13.10.dist-info/entry_points.txt
nimbus_splash-1.13.10.dist-info/top_level.txt
nimbus_splash-1.13.10.dist-info/RECORD
