Metadata-Version: 2.4
Name: nimbus_splash
Version: 1.13.10
Summary: A package to make life easier when using the University of Bath's cloud computing suite for Orca calculations.
Home-page: https://gitlab.com/kragskow-group/nimbus_splash
Author: Jon Kragskow
Author-email: jgck20@bath.ac.uk
Project-URL: Bug Tracker, https://gitlab.com/kragskow-group/nimbus_splash/-/issues
Project-URL: Documentation, https://www.kragskow.group/nimbus_splash/index.html
Classifier: Programming Language :: Python :: 3
Classifier: License :: OSI Approved :: GNU General Public License v3 (GPLv3)
Classifier: Operating System :: OS Independent
Requires-Python: >=3.10
License-File: LICENSE
Requires-Dist: numpy>=2.1.3
Requires-Dist: xyz_py>=5.19.2
Requires-Dist: orto>=1.1.1
Requires-Dist: termcolor
Dynamic: author
Dynamic: author-email
Dynamic: classifier
Dynamic: description
Dynamic: description-content-type
Dynamic: home-page
Dynamic: license-file
Dynamic: project-url
Dynamic: requires-dist
Dynamic: requires-python
Dynamic: summary
